AUTHORS.rst
CONTRIBUTING.rst
HISTORY.rst
LICENSE
MANIFEST.in
README.rst
setup.cfg
setup.py
covid_data_by_zip_code/__init__.py
covid_data_by_zip_code/download.py
covid_data_by_zip_code.egg-info/PKG-INFO
covid_data_by_zip_code.egg-info/SOURCES.txt
covid_data_by_zip_code.egg-info/dependency_links.txt
covid_data_by_zip_code.egg-info/not-zip-safe
covid_data_by_zip_code.egg-info/top_level.txt
docs/Makefile
docs/authors.rst
docs/conf.py
docs/contributing.rst
docs/history.rst
docs/index.rst
docs/installation.rst
docs/make.bat
docs/readme.rst
docs/usage.rst
tests/__init__.py
tests/test_covid_data_by_zip_code.py