Metadata-Version: 1.2
Name: covid-data-by-zip-code
Version: 0.1.4
Summary: this package provides a streamlined way to download covid data by state
Home-page: https://github.com/HaigangLiu/covid_data_by_zip_code
Author: Haigang Liu
Author-email: liuhaigang1989@gmail.com
License: MIT license
Keywords: covid_data_by_zip_code
Platform: UNKNOWN
Classifier: Development Status :: 2 - Pre-Alpha
Classifier: Intended Audience :: Developers
Classifier: License :: OSI Approved :: MIT License
Classifier: Natural Language :: English
Classifier: Programming Language :: Python :: 3
Classifier: Programming Language :: Python :: 3.5
Classifier: Programming Language :: Python :: 3.6
Classifier: Programming Language :: Python :: 3.7
Classifier: Programming Language :: Python :: 3.8
Requires-Python: >=3.5
